{
  "slug": "dr-steven-tijerina",
  "name": "Dr. Steven Tijerina, PT, DPT, Cert. MDT",
  "credentials": "PT, DPT, Cert. MDT",
  "bio": "Dr. Steven Tijerina is the US Director of Integrated Pelvic Care (IPC), a clinical network specializing in pelvic-floor physical therapy and men's pelvic health education. He directs clinical operations and education programs across IPC's US partner clinics, training a new generation of pelvic-floor physical therapists in the IPC methodology — the same framework that informs the calculations and educational content in this app.\n\nA Doctor of Physical Therapy with a Cert. MDT (Mechanical Diagnosis and Therapy) credential, Dr. Tijerina brings a movement-science lens to pelvic dysfunction. His clinical work focuses on how postural patterns, breathing mechanics, and pelvic-floor coordination interact to drive the symptoms that bring most men to a urologist in the first place — urgency, weak stream, incomplete emptying, post-void dribbling, nocturia. Many of these patterns respond to physical therapy when they're caught early, before surgical or pharmacologic intervention becomes the default first answer. The earlier the pattern is named, the more options remain on the table.\n\nFor My Flow Check, Dr. Tijerina serves as medical reviewer for every patient-education article published on the site. His review focuses on clinical accuracy first — does the article match what a clinician would actually teach a patient at the first visit? — and clarity second. He believes patient education has to be honest about what a 3-day bladder diary can and cannot reveal, and what realistic next steps actually look like when a pattern is identified. No oversold promises, no fear-mongering. Just the data and what to do with it.",
  "affiliations": ["Integrated Pelvic Care (IPC)"],
  "linkedIn": "https://www.linkedin.com/in/stevenatijerina/"
}
